zh_doclint/__init__.py
zh_doclint/detect_errors.py
zh_doclint/error_detection.py
zh_doclint/error_display.py
zh_doclint/lcs.py
zh_doclint/main.py
zh_doclint/metadata.py
zh_doclint/mistune_patch.py
zh_doclint/preprocessor.py
zh_doclint-0.1.2.dist-info/DESCRIPTION.rst
zh_doclint-0.1.2.dist-info/METADATA
zh_doclint-0.1.2.dist-info/RECORD
zh_doclint-0.1.2.dist-info/WHEEL
zh_doclint-0.1.2.dist-info/entry_points.txt
zh_doclint-0.1.2.dist-info/metadata.json
zh_doclint-0.1.2.dist-info/top_level.txt
