Metadata-Version: 2.0
Name: zh-doclint
Version: 0.1.2
Summary: automated checker of chinese document.
Home-page: UNKNOWN
Author: huntzhan
Author-email: programmer.zhx@gmail.com
License: UNKNOWN
Platform: UNKNOWN
Classifier: License :: OSI Approved :: MIT License
Classifier: Development Status :: 1 - Planning
Classifier: Intended Audience :: Developers
Classifier: Topic :: Software Development :: Libraries
Classifier: Programming Language :: Python :: 2.7
Classifier: Programming Language :: Python :: 3.3
Classifier: Programming Language :: Python :: 3.4
Classifier: Programming Language :: Python :: 3.5
Requires-Dist: click
Requires-Dist: future
Requires-Dist: mistune (==0.7.3)
